README.txt
setup.py
collective/__init__.py
collective.unresettableuser.egg-info/PKG-INFO
collective.unresettableuser.egg-info/SOURCES.txt
collective.unresettableuser.egg-info/dependency_links.txt
collective.unresettableuser.egg-info/entry_points.txt
collective.unresettableuser.egg-info/namespace_packages.txt
collective.unresettableuser.egg-info/not-zip-safe
collective.unresettableuser.egg-info/requires.txt
collective.unresettableuser.egg-info/top_level.txt
collective/unresettableuser/__init__.py
collective/unresettableuser/configure.zcml
collective/unresettableuser/tests.py
collective/unresettableuser/Extensions/install.py
collective/unresettableuser/browser/__init__.py
collective/unresettableuser/browser/configure.zcml
collective/unresettableuser/browser/password_form.py
collective/unresettableuser/i18n/plone-it.po
collective/unresettableuser/i18n/plone.pot
collective/unresettableuser/i18n/rebuild.sh
collective/unresettableuser/profiles/default/actionicons.xml
collective/unresettableuser/profiles/default/controlpanel.xml
collective/unresettableuser/profiles/default/memberdata_properties.xml
collective/unresettableuser/profiles/default/metadata.xml
collective/unresettableuser/profiles/default/skins.xml
collective/unresettableuser/profiles/uninstall/skins.xml
collective/unresettableuser/skins/unresettableuser/mail_password.py
collective/unresettableuser/skins/unresettableuser/mail_password.py.metadata
collective/unresettableuser/skins/unresettableuser/password_form.pt
collective/unresettableuser/skins/unresettableuser/password_form.pt.metadata
collective/unresettableuser/skins/unresettableuser/personalize_form.cpt
collective/unresettableuser/skins/unresettableuser/personalize_form.cpt.metadata
collective/unresettableuser/skins/unresettableuser/plone_change_password.py
collective/unresettableuser/skins/unresettableuser/prefs_user_edit.cpy
collective/unresettableuser/skins/unresettableuser/prefs_user_edit.cpy.metadata
docs/HISTORY.txt
docs/INSTALL.txt
docs/LICENSE.GPL
docs/LICENSE.txt