Metadata-Version: 1.0
Name: collective.unresettableuser
Version: 0.2.0
Summary: Additional option for Plone users, that make the reset password operation not available
Home-page: http://plone.org/products/collective.unresettableuser
Author: RedTurtle Technology
Author-email: sviluppoplone@redturtle.net
License: GPL
Keywords: plone user reset password
Platform: UNKNOWN
Classifier: Framework :: Plone
Classifier: Framework :: Plone :: 3.3
Classifier: Programming Language :: Python
Classifier: Development Status :: 5 - Production/Stable
